allauth/__init__.py
allauth/app_settings.py
allauth/decorators.py
allauth/exceptions.py
allauth/models.py
allauth/ratelimit.py
allauth/tests.py
allauth/urls.py
allauth/utils.py
allauth/account/__init__.py
allauth/account/adapter.py
allauth/account/admin.py
allauth/account/app_settings.py
allauth/account/apps.py
allauth/account/auth_backends.py
allauth/account/decorators.py
allauth/account/forms.py
allauth/account/managers.py
allauth/account/models.py
allauth/account/signals.py
allauth/account/tests.py
allauth/account/urls.py
allauth/account/utils.py
allauth/account/views.py
allauth/account/management/__init__.py
allauth/account/management/commands/__init__.py
allauth/account/management/commands/account_unsetmultipleprimaryemails.py
allauth/account/migrations/0001_initial.py
allauth/account/migrations/0002_email_max_length.py
allauth/account/migrations/__init__.py
allauth/account/templatetags/__init__.py
allauth/account/templatetags/account.py
allauth/socialaccount/__init__.py
allauth/socialaccount/adapter.py
allauth/socialaccount/admin.py
allauth/socialaccount/app_settings.py
allauth/socialaccount/apps.py
allauth/socialaccount/fields.py
allauth/socialaccount/forms.py
allauth/socialaccount/helpers.py
allauth/socialaccount/models.py
allauth/socialaccount/signals.py
allauth/socialaccount/tests.py
allauth/socialaccount/urls.py
allauth/socialaccount/views.py
allauth/socialaccount/migrations/0001_initial.py
allauth/socialaccount/migrations/0002_token_max_lengths.py
allauth/socialaccount/migrations/0003_extra_data_default_dict.py
allauth/socialaccount/migrations/__init__.py
allauth/socialaccount/providers/__init__.py
allauth/socialaccount/providers/agave/__init__.py
allauth/socialaccount/providers/agave/provider.py
allauth/socialaccount/providers/agave/tests.py
allauth/socialaccount/providers/agave/urls.py
allauth/socialaccount/providers/agave/views.py
allauth/socialaccount/providers/amazon/__init__.py
allauth/socialaccount/providers/amazon/provider.py
bokhakpack-1.0.0.dist-info/METADATA
bokhakpack-1.0.0.dist-info/WHEEL
bokhakpack-1.0.0.dist-info/top_level.txt
bokhakpack-1.0.0.dist-info/RECORD
