Metadata-Version: 2.1
Name: bokhakpack
Version: 1.0.0
Summary: rest-auth, allauth
Home-page: UNKNOWN
Author: dudcks
Author-email: dudcks3886@naver.com
License: UNKNOWN
Platform: UNKNOWN
